pycbcount/__init__.py
pycbcount/blood_values.py
pycbcount/cbc_metrics.py
pycbcount-0.0.1.dist-info/LICENSE
pycbcount-0.0.1.dist-info/METADATA
pycbcount-0.0.1.dist-info/WHEEL
pycbcount-0.0.1.dist-info/top_level.txt
pycbcount-0.0.1.dist-info/RECORD
