Metadata-Version: 2.1
Name: pycbcount
Version: 0.0.1
Summary: A small example package
Home-page: https://github.com/OliLov/pycbcount
Author: Oliver Lövström
Author-email: Oliver Lövström <oliver.lovstrom@gmail.com>
Project-URL: Homepage, https://github.com/OliLov/pycbcount
Project-URL: Issues, https://github.com/OliLov/pycbcount/issues
Classifier: Programming Language :: Python :: 3
Classifier: License :: OSI Approved :: MIT License
Classifier: Operating System :: OS Independent
Requires-Python: >=3.6
License-File: LICENSE
